plone.app.lockingbehavior-2.0.3-py3.13-nspkg.pth
plone/app/lockingbehavior/__init__.py
plone/app/lockingbehavior/behaviors.py
plone/app/lockingbehavior/configure.zcml
plone/app/lockingbehavior/handlers.py
plone/app/lockingbehavior/testing.py
plone/app/lockingbehavior/tests/__init__.py
plone/app/lockingbehavior/tests/test_locking.py
plone_app_lockingbehavior-2.0.3.dist-info/METADATA
plone_app_lockingbehavior-2.0.3.dist-info/WHEEL
plone_app_lockingbehavior-2.0.3.dist-info/entry_points.txt
plone_app_lockingbehavior-2.0.3.dist-info/namespace_packages.txt
plone_app_lockingbehavior-2.0.3.dist-info/top_level.txt
plone_app_lockingbehavior-2.0.3.dist-info/RECORD
