Metadata-Version: 2.4
Name: plone.app.lockingbehavior
Version: 2.0.3
Summary: Locking integration for dexterity content objects.
Home-page: https://github.com/plone/plone.app.lockingbehavior/
Author: Plone Foundation
Author-email: mailto:dexterity-development@googlegroups.com
License: GPL version 2
Keywords: dexterity locking behavior plone
Classifier: Development Status :: 5 - Production/Stable
Classifier: Framework :: Plone
Classifier: Framework :: Plone :: 6.0
Classifier: Framework :: Plone :: 6.1
Classifier: Framework :: Plone :: Core
Classifier: Framework :: Zope2
Classifier: Framework :: Zope :: 5
Classifier: License :: OSI Approved :: GNU General Public License v2 (GPLv2)
Classifier: Programming Language :: Python
Classifier: Programming Language :: Python :: 3.8
Classifier: Programming Language :: Python :: 3.9
Classifier: Programming Language :: Python :: 3.10
Classifier: Programming Language :: Python :: 3.11
Classifier: Programming Language :: Python :: 3.12
Classifier: Topic :: Software Development :: Libraries :: Python Modules
Requires-Python: >=3.8
Requires-Dist: AccessControl
Requires-Dist: setuptools
Requires-Dist: plone.behavior
Requires-Dist: plone.dexterity>=1.1
Requires-Dist: plone.locking
Requires-Dist: zExceptions
Requires-Dist: zope.component
Provides-Extra: tests
Requires-Dist: plone.app.testing; extra == "tests"
Requires-Dist: plone.testing; extra == "tests"
Requires-Dist: transaction; extra == "tests"
Dynamic: author
Dynamic: author-email
Dynamic: classifier
Dynamic: description
Dynamic: description-content-type
Dynamic: home-page
Dynamic: keywords
Dynamic: license
Dynamic: provides-extra
Dynamic: requires-dist
Dynamic: requires-python
Dynamic: summary
